django_toggle_m2m/__init__.py
django_toggle_m2m/__version__.py
django_toggle_m2m/toggle.py
django_toggle_m2m-0.0.6.dist-info/LICENSE
django_toggle_m2m-0.0.6.dist-info/METADATA
django_toggle_m2m-0.0.6.dist-info/WHEEL
django_toggle_m2m-0.0.6.dist-info/top_level.txt
django_toggle_m2m-0.0.6.dist-info/RECORD
