Metadata-Version: 2.1
Name: django-toggle-m2m
Version: 0.0.6
Summary: Django package for generating methods for toggling ManyToMany relationship entries in models
Home-page: https://github.com/wencakisa/django-toggle-m2m
Author: Ventsislav Tashev
Author-email: wencakisa@gmail.com
License: MIT
Platform: UNKNOWN
Classifier: License :: OSI Approved :: MIT License
Classifier: Programming Language :: Python
Classifier: Programming Language :: Python :: 3
Classifier: Programming Language :: Python :: 3.7
Classifier: Programming Language :: Python :: Implementation :: CPython
Requires-Python: >=3.6.0
Requires-Dist: django
